cubemap_splitter/__init__.py
cubemap_splitter/cubemap.py
cubemap_splitter/file_path.py
cubemap_splitter/image.py
cubemap_splitter/image_format.py
cubemap_splitter/image_splitter.py
cubemap_splitter/image_writer.py
cubemap_splitter-0.1.1.dist-info/METADATA
cubemap_splitter-0.1.1.dist-info/WHEEL
cubemap_splitter-0.1.1.dist-info/top_level.txt
cubemap_splitter-0.1.1.dist-info/RECORD
