Metadata-Version: 2.1
Name: cubemap-splitter
Version: 0.1.1
Summary: Python library for automatically splitting and writing cubemap subset images
Home-page: https://github.com/paulburgess1357/Cubemap-Splitter
Author: Paul Burgess
Author-email: paulburgess1357@gmail.com
License: MIT
Platform: UNKNOWN
Classifier: License :: OSI Approved :: MIT License
Classifier: Programming Language :: Python :: 3
Requires-Dist: opencv-python
Requires-Dist: numpy (<1.19.4)
